extensions/bits_defs.py
extensions/math_defs.py
extensions/strings_defs.py
extensions/turtle_defs.py
ibdp_classes/__init__.py
ibdp_classes/__main__.py
ibdp_classes/ibdp_classes.py
ibdp_classes-0.6.0.dist-info/LICENSE
ibdp_classes-0.6.0.dist-info/METADATA
ibdp_classes-0.6.0.dist-info/WHEEL
ibdp_classes-0.6.0.dist-info/top_level.txt
ibdp_classes-0.6.0.dist-info/RECORD
