Metadata-Version: 2.1
Name: ibdp-classes
Version: 0.6.0
Summary: An interpreter for pseudocode similar to that used in IBDP Computer Science courses.
Author-email: Richard Ambler <rambler@wya.top>
Project-URL: Homepage, https://github.com/ram6ler/ibdp_classes/tree/trunk
Project-URL: Bug Tracker, https://github.com/ram6ler/ibdp_classes/issues
Classifier: Programming Language :: Python :: 3
Classifier: License :: OSI Approved :: MIT License
Classifier: Operating System :: OS Independent
Requires-Python: >=3.12
License-File: LICENSE
